painface/__init__.py
painface/grimacecombo.py
painface/kurtosis.py
painface-0.1.1.dist-info/METADATA
painface-0.1.1.dist-info/WHEEL
painface-0.1.1.dist-info/top_level.txt
painface-0.1.1.dist-info/RECORD
