Metadata-Version: 2.1
Name: painface
Version: 0.1.1
Summary: CSV parsing and analysis for PainFace generated CSVs
Home-page: UNKNOWN
Author: Rohan Ray, Rahul Patel
Author-email: painfaceanalysis@gmail.com
License: MIT
Platform: UNKNOWN
Classifier: Programming Language :: Python :: 3
Classifier: Operating System :: OS Independent
Requires-Python: >=3.6
Requires-Dist: numpy
Requires-Dist: pandas
Requires-Dist: scipy
Requires-Dist: matplotlib
